[
    {
        "advertiserUrl": "springfreetrampoline.com",
        "campaignUrl": "springfreetrampoline.ca",
        "trackingLink": "https://springfree-trampolineca.pxf.io/c/4797259/1769243/20835"
    },
    {
        "advertiserUrl": "springfreetrampoline.com",
        "campaignUrl": "springfreetrampoline.com",
        "trackingLink": "https://springfree-trampoline.pxf.io/c/4797259/1569543/18258"
    },
    {
        "advertiserUrl": "prohockeylife.com",
        "campaignUrl": "prohockeylife.com",
        "trackingLink": "https://prohockeylife.pxf.io/c/4797259/979143/12925"
    },
    {
        "advertiserUrl": "wish.com",
        "campaignUrl": "wish.com",
        "trackingLink": "https://wish.pxf.io/c/4797259/899103/12396"
    },
    {
        "advertiserUrl": "easyship.com",
        "campaignUrl": "easyship.com",
        "trackingLink": "https://easyship.ilbqy6.net/c/4797259/666308/10435"
    },
    {
        "advertiserUrl": "decathlon.ca",
        "campaignUrl": "decathlon.ca",
        "trackingLink": "https://decathlon-canada.mkr3.net/c/4797259/642729/10224"
    },
    {
        "advertiserUrl": "fanatics.com",
        "campaignUrl": "fanatics.com",
        "trackingLink": "https://fanatics.93n6tx.net/c/4797259/586570/9663"
    },
    {
        "advertiserUrl": "marks.com",
        "campaignUrl": "marks.com",
        "trackingLink": "https://marks.r37x9j.net/c/4797259/505590/8679"
    },
    {
        "advertiserUrl": "impact.com",
        "campaignUrl": "impact.com",
        "trackingLink": "https://impact-referral-partnerships.sjv.io/c/4797259/749356/10925"
    },
    {
        "advertiserUrl": "adidas.com.au",
        "campaignUrl": "adidas.com.au",
        "trackingLink": "https://adidas-australia.pxf.io/c/4797259/408139/7362"
    },
    {
        "advertiserUrl": "points.com",
        "campaignUrl": "points.com",
        "trackingLink": "https://marriott.pxf.io/c/4797259/321373/4937"
    },
    {
        "advertiserUrl": "points.com",
        "campaignUrl": "points.com",
        "trackingLink": "https://hilton.ijrn.net/c/4797259/314255/4823"
    },
    {
        "advertiserUrl": "points.com",
        "campaignUrl": "points.com",
        "trackingLink": "https://ihg.hmxg.net/c/4797259/310617/4797"
    },
    {
        "advertiserUrl": "points.com",
        "campaignUrl": "points.com",
        "trackingLink": "https://swa.eyjo.net/c/4797259/302888/4705"
    }
]